innoframework/__init__.py
innoframework/data/__init__.py
innoframework/data/data_module.py
innoframework/data/dataset.py
innoframework/data_handler.py
innoframework/main.py
innoframework/ui.py
innoframework/utils/__init__.py
innoframework/utils/main.py
innoframework/wrappers/__init__.py
innoframework/wrappers/main.py
innoframework-0.1.1.dist-info/LICENSE
innoframework-0.1.1.dist-info/WHEEL
innoframework-0.1.1.dist-info/METADATA
innoframework-0.1.1.dist-info/RECORD
