Metadata-Version: 2.1
Name: innoframework
Version: 0.1.1
Summary: 
Author: Kazybek Askarbek
Author-email: k.askarbek@innopolis.university
Requires-Python: >=3.8,<4.0
Classifier: Programming Language :: Python :: 3
Classifier: Programming Language :: Python :: 3.10
Classifier: Programming Language :: Python :: 3.8
Classifier: Programming Language :: Python :: 3.9
Requires-Dist: albumentations (>=1.1.0,<2.0.0)
Requires-Dist: h5py (>=3.6.0,<4.0.0)
Requires-Dist: hydra-core (>=1.1.1,<2.0.0)
Requires-Dist: pytorch-lightning (>=1.5.10,<2.0.0)
Requires-Dist: segmentation-models-pytorch (>=0.2.1,<0.3.0)
Requires-Dist: setuptools (==59.5.0)
Requires-Dist: sklearn (>=0.0,<0.1)
Requires-Dist: streamlit (>=1.5.1,<2.0.0)
Requires-Dist: torch (>=1.10.2,<2.0.0)
